examples/basic_usage.py
springrank/__init__.py
springrank/springrank.py
springrank-0.0.10.dist-info/licenses/LICENSE
springrank-0.0.10.dist-info/METADATA
springrank-0.0.10.dist-info/WHEEL
springrank-0.0.10.dist-info/top_level.txt
springrank-0.0.10.dist-info/RECORD
