Metadata-Version: 2.4
Name: SpringRank
Version: 0.0.10
Summary: SpringRank: A physical model for efficient ranking in networks
Author: Caterina De Bacco, Cris Moore
Author-email: Daniel Larremore <daniel.larremore@colorado.edu>
Maintainer-email: Daniel Larremore <daniel.larremore@colorado.edu>
License-Expression: GPL-3.0-or-later
Project-URL: Homepage, https://github.com/LarremoreLab/SpringRank
Project-URL: Repository, https://github.com/LarremoreLab/SpringRank
Project-URL: Issues, https://github.com/LarremoreLab/SpringRank/issues
Keywords: rankings,SpringRank
Classifier: Development Status :: 4 - Beta
Classifier: Intended Audience :: Science/Research
Classifier: Operating System :: OS Independent
Classifier: Programming Language :: Python :: 3
Classifier: Programming Language :: Python :: 3.6
Classifier: Programming Language :: Python :: 3.7
Classifier: Programming Language :: Python :: 3.8
Classifier: Programming Language :: Python :: 3.9
Classifier: Programming Language :: Python :: 3.10
Classifier: Programming Language :: Python :: 3.11
Classifier: Programming Language :: Python :: 3.12
Classifier: Natural Language :: English
Classifier: Topic :: Scientific/Engineering
Requires-Python: >=3.6
License-File: LICENSE
Requires-Dist: numpy
Requires-Dist: scipy
Dynamic: license-file
